virtualhome_eval
