Metadata-Version: 2.1
Name: virtualhome_eval
Version: 0.1.1
Summary: Embodied agent interface evaluation for VirtualHome
Home-page: https://github.com/embodied-agent-eval/virtualhome_eval
Author: stanford
Classifier: Programming Language :: Python :: 3
Classifier: License :: OSI Approved :: MIT License
Classifier: Operating System :: OS Independent
Requires-Python: >=3.8
License-File: LICENSE
Requires-Dist: pddlgym
Requires-Dist: fire
Requires-Dist: lark
Requires-Dist: openai
Requires-Dist: ipdb
Requires-Dist: networkx >=3.1
Requires-Dist: numpy >=1.20.0
